dask_clickhouse/__init__.py
dask_clickhouse/core.py
dask_clickhouse-0.3.0.dist-info/LICENSE
dask_clickhouse-0.3.0.dist-info/WHEEL
dask_clickhouse-0.3.0.dist-info/METADATA
dask_clickhouse-0.3.0.dist-info/RECORD
