Metadata-Version: 2.1
Name: dask-clickhouse
Version: 0.3.0
Summary: Dask integration for Clickhouse
Home-page: https://github.com/mharrisb1/dask-clickhouse
License: MIT
Author: Michael Harris
Author-email: mharris@luabase.com
Requires-Python: >=3.8,<3.11
Classifier: License :: OSI Approved :: MIT License
Classifier: Programming Language :: Python :: 3
Classifier: Programming Language :: Python :: 3.10
Classifier: Programming Language :: Python :: 3.8
Classifier: Programming Language :: Python :: 3.9
Requires-Dist: dask (>=2022.7.1,<2023.0.0)
Requires-Dist: ibis-framework[clickhouse] (>=3.1.0,<4.0.0)
Requires-Dist: pyarrow (>=9.0.0,<10.0.0)
Project-URL: Repository, https://github.com/mharrisb1/dask-clickhouse
